CHANGES.txt
MANIFEST.in
README.md
setup.py
GeobricksGISVector.egg-info/PKG-INFO
GeobricksGISVector.egg-info/SOURCES.txt
GeobricksGISVector.egg-info/dependency_links.txt
GeobricksGISVector.egg-info/requires.txt
GeobricksGISVector.egg-info/top_level.txt
geobricks_gis_vector/__init__.py
geobricks_gis_vector/__init__.pyc
geobricks_gis_vector/config/__init__.py
geobricks_gis_vector/config/__init__.pyc
geobricks_gis_vector/config/config.py
geobricks_gis_vector/config/config.pyc
geobricks_gis_vector/core/__init__.py
geobricks_gis_vector/core/__init__.pyc
geobricks_gis_vector/core/vector.py
geobricks_gis_vector/core/vector.pyc