Metadata-Version: 1.0
Name: GeobricksGISVector
Version: 0.0.2
Summary: Geobricks library to process vector layers.
Home-page: http://pypi.python.org/pypi/GeobricksGISVector/
Author: Simone Murzilli; Guido Barbaglia
Author-email: geobrickspy@gmail.com
License: LICENSE.txt
Keywords: geobricks,geoserver,gis,vector
Platform: UNKNOWN
